setup.cfg
setup.py
biosignal/__init__.py
biosignal.egg-info/PKG-INFO
biosignal.egg-info/SOURCES.txt
biosignal.egg-info/dependency_links.txt
biosignal.egg-info/not-zip-safe
biosignal.egg-info/top_level.txt