Metadata-Version: 1.0
Name: biosignal
Version: 0.0.2
Summary: A library for processing and analysing physiological
Home-page: http://github.com/EmlynC/python-biosignal
Author: Emlyn Clay
Author-email: eclay101@gmail.com
License: MIT
Platform: UNKNOWN
